PyAppBuilder/__init__.py
PyAppBuilder-0.1.1.dist-info/LICENSE
PyAppBuilder-0.1.1.dist-info/METADATA
PyAppBuilder-0.1.1.dist-info/WHEEL
PyAppBuilder-0.1.1.dist-info/top_level.txt
PyAppBuilder-0.1.1.dist-info/RECORD
