Metadata-Version: 2.1
Name: PyAppBuilder
Version: 0.1.1
Summary: makes applications
Home-page: UNKNOWN
Author: Technical Earth
Author-email: technicalearth0@gmail.com
License: UNKNOWN
Keywords: python,GUI,app,tkinter,PyQt5,PYPI
Platform: UNKNOWN
Classifier: Development Status :: 1 - Planning
Classifier: Intended Audience :: Developers
Classifier: Programming Language :: Python :: 3
Classifier: Operating System :: Unix
Classifier: Operating System :: MacOS :: MacOS X
Classifier: Operating System :: Microsoft :: Windows
Requires-Dist: PyQt5
Requires-Dist: PyQt5-stubs
Requires-Dist: PyQtWebEngine
